[
  {
    "id": "alexandre-sarran",
    "email": "alexandre.sarran@egliselyongerland.org",
    "firstname": "Alexandre",
    "lastname": "Sarran"
  },
  {
    "id": "amaury-francais",
    "email": "fra.amaury@gmail.com",
    "firstname": "Amaury",
    "lastname": "Français"
  },
  {
    "id": "amelie-fournier",
    "firstname": "Amélie",
    "lastname": "Fournier",
    "archived": true
  },
  {
    "id": "amy-haddad",
    "firstname": "Amy",
    "lastname": "Haddad",
    "archived": true
  },
  {
    "id": "anne-julien",
    "firstname": "Anne",
    "lastname": "Julien",
    "archived": true
  },
  {
    "id": "annie-tshika",
    "firstname": "Annie",
    "lastname": "Tshika",
    "archived": true
  },
  {
    "id": "augustin-sarran",
    "email": "alexsarran@gmail.com",
    "firstname": "Augustin",
    "lastname": "Sarran",
    "age": "6-9"
  },
  {
    "id": "aurelie-charles",
    "email": "aurelie.wattiau@laposte.net",
    "firstname": "Aurélie",
    "lastname": "Charles"
  },
  {
    "id": "caedmon-haddad",
    "firstname": "Caedmon",
    "lastname": "Haddad",
    "age": "14-17",
    "archived": true
  },
  {
    "id": "caryn-di-gena",
    "email": "caryn.digena@efca.org",
    "firstname": "Caryn",
    "lastname": "DiGena"
  },
  {
    "id": "charlene-picq",
    "email": "picqcharlene.cnp@gmail.com",
    "firstname": "Charlène",
    "lastname": "Picq"
  },
  {
    "id": "colin-cachard",
    "email": "colin-cachard@orange.fr",
    "firstname": "Colin",
    "lastname": "Cachard"
  },
  {
    "id": "daniel-le-gal",
    "email": "daniel.legal.00@gmail.com",
    "firstname": "Daniel",
    "lastname": "Le Gal"
  },
  {
    "id": "david-bourgeois",
    "firstname": "David",
    "lastname": "Bourgeois",
    "exclude": ["enora-corlay"],
    "archived": true
  },
  {
    "id": "denis-blum",
    "email": "blumdenis@aol.com",
    "firstname": "Denis",
    "lastname": "Blum"
  },
  {
    "id": "dimitri-cobb",
    "firstname": "Dimitri",
    "lastname": "Cobb",
    "archived": true
  },
  {
    "id": "dwight-bornes",
    "firstname": "Dwight",
    "lastname": "Bornes",
    "archived": true
  },
  {
    "id": "elia-grace-exbrayat",
    "email": "exbrayatpv@gmail.com",
    "firstname": "Elia-Grace",
    "lastname": "Exbrayat",
    "age": "10-13"
  },
  {
    "id": "elona-caparros",
    "email": "elona.caparros@icould.com",
    "firstname": "Elona",
    "lastname": "Caparros",
    "age": "14-17"
  },
  {
    "id": "elsa-lelieu",
    "email": "elsamon@hotmail.fr",
    "firstname": "Elsa",
    "lastname": "Lelieu"
  },
  {
    "id": "enora-corlay",
    "firstname": "Énora",
    "lastname": "Corlay",
    "exclude": ["david-bourgeois"],
    "archived": true
  },
  {
    "id": "etienne-gerber",
    "firstname": "Étienne",
    "lastname": "Gerber",
    "archived": true
  },
  {
    "id": "etienne-sarran",
    "email": "etiennesarran@gmail.com",
    "firstname": "Etienne",
    "lastname": "Sarran",
    "age": "14-17"
  },
  {
    "id": "fabrice-lingois",
    "email": "lingois.fabrice@hotmail.fr",
    "firstname": "Fabrice",
    "lastname": "Lingois"
  },
  {
    "id": "flora-julien",
    "firstname": "Flora",
    "lastname": "Julien",
    "archived": true
  },
  {
    "id": "florian-vincenzi",
    "email": "vincenzi.florian@gmail.com",
    "firstname": "Florian",
    "lastname": "Vincenzi"
  },
  {
    "id": "francois-risson",
    "email": "francoisrisson@gmail.com",
    "firstname": "François",
    "lastname": "Risson"
  },
  {
    "id": "gabrielle-ziegler",
    "email": "gabi@zieglers.org",
    "firstname": "Gabriëlle",
    "lastname": "Ziegler"
  },
  {
    "id": "gilles-campoy",
    "email": "gillescampoy42@gmail.com",
    "firstname": "Gilles",
    "lastname": "Campoy"
  },
  {
    "id": "helene-bazille",
    "email": "helene@bazille.fr",
    "firstname": "Hélène",
    "lastname": "Bazille"
  },
  {
    "id": "hyun-joo-exbrayat",
    "email": "exbrayatpv@gmail.com",
    "firstname": "Hyun-Joo",
    "lastname": "Exbrayat"
  },
  {
    "id": "isaque-carreto",
    "firstname": "Isaque",
    "lastname": "Carreto",
    "archived": true
  },
  {
    "id": "ivan-hamelin",
    "firstname": "Ivan",
    "lastname": "Hamelin",
    "age": "14-17",
    "archived": true
  },
  {
    "id": "jean-francois-chanel",
    "email": "sabine.chanel@laposte.net",
    "firstname": "Jean-François",
    "lastname": "Chanel"
  },
  {
    "id": "jean-francois-maniere",
    "email": "jf.maniere@orange.fr",
    "firstname": "Jean-François",
    "lastname": "Manière"
  },
  {
    "id": "jeanne-guilhot",
    "email": "Guilhot.jeanne@gmail.com",
    "firstname": "Jeanne",
    "lastname": "Guilhot"
  },
  {
    "id": "jeronimo-avellaneda",
    "email": "jeronimoavellaneda21@gmail.com",
    "firstname": "Jerónimo",
    "lastname": "Avellaneda",
    "age": "10-13"
  },
  {
    "id": "jonah-haddad",
    "firstname": "Jonah",
    "lastname": "Haddad",
    "archived": true
  },
  {
    "id": "joshua-sims",
    "firstname": "Joshua",
    "lastname": "Sims",
    "archived": true
  },
  {
    "id": "jung-yeon-gosselin",
    "firstname": "Jung-Yeon",
    "lastname": "Gosselin",
    "archived": true
  },
  {
    "id": "kalhou-vang",
    "firstname": "Kalhou",
    "lastname": "Vang",
    "archived": true
  },
  {
    "id": "karine-comte",
    "firstname": "Karine",
    "lastname": "Comte",
    "archived": true
  },
  {
    "id": "kenneth-ziegler",
    "email": "ken@zieglers.org",
    "firstname": "Kenneth",
    "lastname": "Ziegler"
  },
  {
    "id": "laetitia-calabria",
    "email": "calabrialaetitia@gmail.com",
    "firstname": "Laetitia",
    "lastname": "Calabria"
  },
  {
    "id": "laetitia-grare",
    "firstname": "Laetitia",
    "lastname": "Grare",
    "archived": true
  },
  {
    "id": "laetitia-stauffer",
    "email": "staufferlaetitia@gmail.com",
    "firstname": "Laetitia",
    "lastname": "Stauffer"
  },
  {
    "id": "lars-fracheboud",
    "email": "highestpeak.fr@gmail.com",
    "firstname": "Lars",
    "lastname": "Fracheboud"
  },
  {
    "id": "laurent-caparros",
    "email": "lm.caparros@wanadoo.fr",
    "firstname": "Laurent",
    "lastname": "Caparros"
  },
  {
    "id": "lenora-haddad",
    "firstname": "Lenora",
    "lastname": "Haddad",
    "archived": true
  },
  {
    "id": "linda-hamelin",
    "email": "lzhamelin@gmail.com",
    "firstname": "Linda",
    "lastname": "Hamelin"
  },
  {
    "id": "lois-bazille",
    "email": "helene@bazille.fr",
    "firstname": "Loïs",
    "lastname": "Bazille",
    "age": "6-9"
  },
  {
    "id": "lucy-nemoz",
    "email": "lucynemoz@gmail.com",
    "firstname": "Lucy",
    "lastname": "Nemoz"
  },
  {
    "id": "lycia-francais",
    "email": "lycia.francais@gmail.com",
    "firstname": "Lycia",
    "lastname": "French"
  },
  {
    "id": "lydie-exbrayat",
    "email": "exbrayatpv@gmail.com",
    "firstname": "Lydie",
    "lastname": "Exbrayat",
    "age": "14-17"
  },
  {
    "id": "madele-bazille",
    "email": "helene@bazille.fr",
    "firstname": "Madèle",
    "lastname": "Bazille",
    "age": "6-9"
  },
  {
    "id": "mailys-blum",
    "email": "mailysvenet@gmail.com",
    "firstname": "Mailys",
    "lastname": "Blum"
  },
  {
    "id": "marc-descheemaecker",
    "email": "marc.descheemaecker3@gmail.com",
    "firstname": "Marc",
    "lastname": "Descheemaecker"
  },
  {
    "id": "margaret-haddad",
    "firstname": "Margaret",
    "lastname": "Haddad",
    "age": "10-13",
    "archived": true
  },
  {
    "id": "marie-jo-descheemaecker",
    "email": "mariejoseedesch@gmail.com",
    "firstname": "Marie-Jo",
    "lastname": "Descheemaecker"
  },
  {
    "id": "marie-julien",
    "firstname": "Marie",
    "lastname": "Julien",
    "age": "10-13",
    "archived": true
  },
  {
    "id": "marie-noelle-gerber",
    "firstname": "Marie-Noëlle",
    "lastname": "Gerber",
    "archived": true
  },
  {
    "id": "mathilde-portmann",
    "email": "portmannmahilde@yahoo.fr",
    "firstname": "Mathilde",
    "lastname": "Portmann"
  },
  {
    "id": "matthieu-sarran",
    "firstname": "Matthieu",
    "lastname": "Sarran",
    "archived": true
  },
  {
    "id": "mireille-yoyotte-landry",
    "firstname": "Mireille",
    "lastname": "Yoyotte Landry",
    "archived": true
  },
  {
    "id": "myriam-caparros",
    "email": "myriamcap@free.fr",
    "firstname": "Myriam",
    "lastname": "Caparros"
  },
  {
    "id": "naomi-vigne",
    "email": "nao.vigne@gmail.com",
    "firstname": "Naomi",
    "lastname": "Vigné"
  },
  {
    "id": "nathalie-merlano",
    "email": "nathaliemerlano@hotmail.com",
    "firstname": "Nathalie",
    "lastname": "Merlano"
  },
  {
    "id": "orlane-batman",
    "firstname": "Orlane",
    "lastname": "Batman",
    "archived": true
  },
  {
    "id": "pascal-haddad",
    "firstname": "Pascal",
    "lastname": "Haddad",
    "age": "10-13",
    "archived": true
  },
  {
    "id": "pierrick-fournier",
    "firstname": "Pierrick",
    "lastname": "Fournier",
    "archived": true
  },
  {
    "id": "qiqi-zhu",
    "email": "qiqizhu2020@outlook.com",
    "firstname": "Qiqi",
    "lastname": "Zhu"
  },
  {
    "id": "rafaella-bartz-pena",
    "firstname": "Rafaella",
    "lastname": "Bartz Pena",
    "archived": true
  },
  {
    "id": "sabine-chanel",
    "email": "sabine.chanel@laposte.net",
    "firstname": "Sabine",
    "lastname": "Chanel"
  },
  {
    "id": "solange-de-melo",
    "firstname": "Solange",
    "lastname": "De Melo",
    "archived": true
  },
  {
    "id": "soohyun-vang",
    "firstname": "Soohyun",
    "lastname": "Vang",
    "archived": true
  },
  {
    "id": "sophie-vincenzi",
    "email": "sophie.dellacorte@outlook.com",
    "firstname": "Sophie",
    "lastname": "Vincenzi"
  },
  {
    "id": "stephane-hamelin",
    "email": "hamelinsteph@gmail.com",
    "firstname": "Stéphane",
    "lastname": "Hamelin"
  },
  {
    "id": "suzanne-sarran",
    "email": "sarransuzanne@gmail.com",
    "firstname": "Suzanne",
    "lastname": "Sarran"
  },
  {
    "id": "tehele-mpassi",
    "firstname": "Tehele",
    "lastname": "Mpassi",
    "archived": true
  },
  {
    "id": "teresa-carreto",
    "firstname": "Teresa",
    "lastname": "Carreto",
    "archived": true
  },
  {
    "id": "theotime-julien",
    "firstname": "Théotime",
    "lastname": "Julien",
    "age": "14-17",
    "archived": true
  },
  {
    "id": "thierry-comte",
    "firstname": "Thierry",
    "lastname": "Comte",
    "archived": true
  },
  {
    "id": "timothee-exbrayat",
    "email": "exbrayatpv@gmail.com",
    "firstname": "Timothée",
    "lastname": "Exbrayat",
    "age": "14-17"
  },
  {
    "id": "timothee-sarran",
    "email": "sarrantimothee@gmail.com",
    "firstname": "Timothée",
    "lastname": "Sarran",
    "age": "14-17"
  },
  {
    "id": "timothee-vang",
    "firstname": "Timothée",
    "lastname": "Vang",
    "age": "10-13",
    "archived": true
  },
  {
    "id": "tom-kristanek",
    "firstname": "Tom",
    "lastname": "Kristanek",
    "archived": true
  },
  {
    "id": "toyese-oyegoke",
    "firstname": "Toyese",
    "lastname": "Oyegoke",
    "archived": true
  },
  {
    "id": "trina-collet",
    "firstname": "Trina",
    "lastname": "Collet",
    "archived": true
  },
  {
    "id": "vallouise-sarran",
    "email": "Vallouisesarran@gmail.com",
    "firstname": "Vallouise",
    "lastname": "Sarran",
    "age": "10-13"
  },
  {
    "id": "vincent-collet",
    "firstname": "Vincent",
    "lastname": "Collet",
    "archived": true
  },
  {
    "id": "violette-sarran",
    "email": "alexsarran@gmail.com",
    "firstname": "Violette",
    "lastname": "Sarran",
    "age": "6-9"
  },
  {
    "id": "yahel-caparros",
    "email": "myriamcap@free.fr",
    "firstname": "Yahel",
    "lastname": "Caparros",
    "age": "14-17"
  },
  {
    "id": "yi-hsuan-chen",
    "email": "artist5818@gmail.com",
    "firstname": "Yi-Hsuan",
    "lastname": "Chen"
  },
  {
    "id": "yvette-campoy",
    "email": "yvettecampoy@hotmail.com",
    "firstname": "Yvette",
    "lastname": "Campoy"
  }
]
